TAcharts/__init__.py
TAcharts/wrappers.py
TAcharts/indicators/__init__.py
TAcharts/indicators/atr.py
TAcharts/indicators/bollinger.py
TAcharts/indicators/cmf.py
TAcharts/indicators/double_smooth.py
TAcharts/indicators/ema.py
TAcharts/indicators/ichimoku.py
TAcharts/indicators/macd.py
TAcharts/indicators/mmo.py
TAcharts/indicators/renko.py
TAcharts/indicators/roc.py
TAcharts/indicators/rolling.py
TAcharts/indicators/rsi.py
TAcharts/indicators/sdev.py
TAcharts/indicators/sma.py
TAcharts/indicators/td_sequential.py
TAcharts/indicators/tsi.py
TAcharts/utils/__init__.py
TAcharts/utils/apply_across.py
TAcharts/utils/area_between.py
TAcharts/utils/crossover.py
TAcharts/utils/demo_df.py
TAcharts/utils/draw_candlesticks.py
TAcharts/utils/fill_values.py
TAcharts/utils/group_candles.py
TAcharts/utils/intersection.py
TAcharts/utils/ohlcv.py
TAcharts-0.0.29.dist-info/LICENSE
TAcharts-0.0.29.dist-info/METADATA
TAcharts-0.0.29.dist-info/WHEEL
TAcharts-0.0.29.dist-info/top_level.txt
TAcharts-0.0.29.dist-info/RECORD
