Metadata-Version: 2.1
Name: TAcharts
Version: 0.0.29
Summary: TA Charting tool
Home-page: https://github.com/carlfarterson/TAcharts
Author: Carl Farterson
Author-email: carlfarterson@gmail.com
License: MIT
Keywords: TA,technical-analysis,mathematics,algorithms,trading,statistics,crypto,cryptocurrency,ohlc,ohlcv
Platform: UNKNOWN
Classifier: Development Status :: 3 - Alpha
Classifier: Programming Language :: Python :: 3
Classifier: License :: OSI Approved :: MIT License
Classifier: Intended Audience :: Developers
Requires-Python: >=3.6
Requires-Dist: pandas (>=0.21.0)
Requires-Dist: numpy (>=1.0.0)
Requires-Dist: matplotlib (>=2.0.0)
